nwp_consumer/__init__.py
nwp_consumer/py.typed
nwp_consumer/cmd/__init__.py
nwp_consumer/cmd/main.py
nwp_consumer/internal/__init__.py
nwp_consumer/internal/entities/__init__.py
nwp_consumer/internal/entities/coordinates.py
nwp_consumer/internal/entities/modelmetadata.py
nwp_consumer/internal/entities/notification.py
nwp_consumer/internal/entities/parameters.py
nwp_consumer/internal/entities/performance.py
nwp_consumer/internal/entities/postprocess.py
nwp_consumer/internal/entities/repometadata.py
nwp_consumer/internal/entities/tensorstore.py
nwp_consumer/internal/entities/test_coordinates.py
nwp_consumer/internal/entities/test_modelmetadata.py
nwp_consumer/internal/entities/test_parameters.py
nwp_consumer/internal/entities/test_postprocess.py
nwp_consumer/internal/entities/test_repometadata.py
nwp_consumer/internal/entities/test_tensorstore.py
nwp_consumer/internal/handlers/__init__.py
nwp_consumer/internal/handlers/cli.py
nwp_consumer/internal/ports/__init__.py
nwp_consumer/internal/ports/repositories.py
nwp_consumer/internal/ports/services.py
nwp_consumer/internal/repositories/__init__.py
nwp_consumer/internal/repositories/notification_repositories/__init__.py
nwp_consumer/internal/repositories/notification_repositories/dagster.py
nwp_consumer/internal/repositories/notification_repositories/stdout.py
nwp_consumer/internal/repositories/raw_repositories/__init__.py
nwp_consumer/internal/repositories/raw_repositories/ceda.py
nwp_consumer/internal/repositories/raw_repositories/ecmwf_mars.py
nwp_consumer/internal/repositories/raw_repositories/ecmwf_realtime.py
nwp_consumer/internal/repositories/raw_repositories/mo_datahub.py
nwp_consumer/internal/repositories/raw_repositories/noaa_s3.py
nwp_consumer/internal/repositories/raw_repositories/test_ceda.py
nwp_consumer/internal/repositories/raw_repositories/test_ecmwf_mars.py
nwp_consumer/internal/repositories/raw_repositories/test_ecmwf_realtime.py
nwp_consumer/internal/repositories/raw_repositories/test_mo_datahub.py
nwp_consumer-1.1.33.dist-info/METADATA
nwp_consumer-1.1.33.dist-info/WHEEL
nwp_consumer-1.1.33.dist-info/entry_points.txt
nwp_consumer-1.1.33.dist-info/top_level.txt
nwp_consumer-1.1.33.dist-info/RECORD
