Metadata-Version: 2.4
Name: nwp-consumer
Version: 1.1.33
Summary: Tool for aggregating raw NWP files into .zarr files
Author-email: Sol Cotton <sol@openclimatefix.org>
License: MIT License
Project-URL: repository, https://github.com/openclimatefix/nwp-consumer
Classifier: Programming Language :: Python :: 3
Requires-Python: <3.13,>=3.12
Requires-Dist: dask==2024.8.1
Requires-Dist: eccodes==2.38.3
Requires-Dist: ecmwf-api-client==1.6.3
Requires-Dist: cfgrib==0.9.14.1
Requires-Dist: dagster-pipes==1.9.3
Requires-Dist: joblib==1.4.2
Requires-Dist: numcodecs==0.15.1
Requires-Dist: numpy==2.1.0
Requires-Dist: ocf-blosc2==0.0.11
Requires-Dist: psutil==6.0.0
Requires-Dist: returns==0.24.0
Requires-Dist: s3fs==2024.9.0
Requires-Dist: xarray==2025.1.0
Requires-Dist: zarr==2.18.3
